testcase/__init__.py
testcase/maxminnorm.py
testcase/tftime_test.py
torchfun/__init__.py
torchfun/datasets.py
torchfun/functional.py
torchfun/metrics.py
torchfun/nn.py
torchfun/path.py
torchfun/torchfun.py
torchfun/transforms.py
torchfun/types.py
torchfun/ui.py
torchfun/utils.py
torchfun/version
torchfun/tools/__init__.py
torchfun/tools/imgformat.py
torchfun/tools/paper_image_extractor.py
torchfun/tools/textformat.py
torchfun-1.0.96.dist-info/LICENSE
torchfun-1.0.96.dist-info/METADATA
torchfun-1.0.96.dist-info/WHEEL
torchfun-1.0.96.dist-info/entry_points.txt
torchfun-1.0.96.dist-info/top_level.txt
torchfun-1.0.96.dist-info/RECORD
