Metadata-Version: 2.1
Name: torchfun
Version: 1.0.96
Summary: A collection of functions/classes that supplements torch functionality.
Home-page: https://github.com/sorenchiron/torchfun
Author: CHEN Si Yu
Author-email: sychen@zju.edu.cn
Classifier: Programming Language :: Python
Classifier: License :: OSI Approved :: MIT License
Classifier: Operating System :: OS Independent
Classifier: Topic :: Scientific/Engineering :: Artificial Intelligence
Classifier: License :: OSI Approved :: MIT License
License-File: LICENSE
Requires-Dist: numpy
Requires-Dist: torch
Requires-Dist: torchvision
Requires-Dist: matplotlib >=3.0.0
Requires-Dist: Pillow
Requires-Dist: scipy
Requires-Dist: tqdm
Requires-Dist: psutil
Requires-Dist: tensorboardX
Requires-Dist: imageio
Requires-Dist: img2pdf
